softwaretoolparra/Expintegral.py
softwaretoolparra/NewtonQuadra.py
softwaretoolparra/__init__.py
softwaretoolparra/basinofdistraction.py
softwaretoolparra/matrix_dot.py
softwaretoolparra/ols.py
softwaretoolparra-0.7.dist-info/METADATA
softwaretoolparra-0.7.dist-info/WHEEL
softwaretoolparra-0.7.dist-info/top_level.txt
softwaretoolparra-0.7.dist-info/RECORD
