Metadata-Version: 2.1
Name: softwaretoolparra
Version: 0.7
Summary: Library written by Dennis Guo in the light of some ideas from Stefano
Home-page: UNKNOWN
Author: Dennis Guo
Author-email: guohq@bc.edu
License: MIT
Platform: UNKNOWN
Classifier: Programming Language :: Python :: 3
